myst/__init__.py
myst_auth-0.0.1.dist-info/LICENSE
myst_auth-0.0.1.dist-info/METADATA
myst_auth-0.0.1.dist-info/WHEEL
myst_auth-0.0.1.dist-info/top_level.txt
myst_auth-0.0.1.dist-info/RECORD
